pyfao56/__init__.py
pyfao56/autoirrigate.py
pyfao56/irrigation.py
pyfao56/model.py
pyfao56/parameters.py
pyfao56/refet.py
pyfao56/soil_profile.py
pyfao56/update.py
pyfao56/weather.py
pyfao56/custom/__init__.py
pyfao56/custom/azmet_maricopa.py
pyfao56/custom/example_soil.py
pyfao56/tools/__init__.py
pyfao56/tools/forecast.py
pyfao56/tools/soil_water.py
pyfao56/tools/statistics.py
pyfao56/tools/visualization.py
pyfao56-1.3.0.dist-info/LICENSE.md
pyfao56-1.3.0.dist-info/METADATA
pyfao56-1.3.0.dist-info/WHEEL
pyfao56-1.3.0.dist-info/top_level.txt
pyfao56-1.3.0.dist-info/RECORD
