Metadata-Version: 2.1
Name: pyfao56
Version: 1.3.0
Summary: FAO-56 Evapotranspiration in Python
Home-page: http://github.com/kthorp/pyfao56
Author: Dr. Kelly R. Thorp
Author-email: kelly.thorp@usda.gov
License: Public Domain
Project-URL: Source, http://github.com/kthorp/pyfao56
Project-URL: Bug Tracker, http://github.com/kthorp/pyfao56/issues
Classifier: Programming Language :: Python :: 3
Classifier: Operating System :: OS Independent
Requires-Python: >=3.7
License-File: LICENSE.md
Requires-Dist: matplotlib
Requires-Dist: pandas
Requires-Dist: numpy
Requires-Dist: requests
Requires-Dist: urllib3
